<ImageInfo><CustomerName>Karen Harris</CustomerName><CustomerPhone>2144172197</CustomerPhone><CustomerEmail>yaya.karenharris@gmail.com</CustomerEmail><TimeEntered>9/4/2018:8:03 PM</TimeEntered><ArtistName>Karen Harris</ArtistName><ArtTitle>Tango</ArtTitle><Dimensions>40x30</Dimensions><Medium>oil</Medium><Price>$1600</Price><ImagePath>C:\Inetpub\vhosts\planoartassociation.org\httpdocs\App_Data\Uploaded_Image_Libraries\Global_Reflections\yaya.karenharris.gmail.com\Karen-Tango-Master.jpg</ImagePath></ImageInfo>