<ImageInfo><CustomerName>Katherine Wang</CustomerName><CustomerPhone>2145175513</CustomerPhone><CustomerEmail>wkatherine114@gmail.com</CustomerEmail><TimeEntered>3/11/2018:12:38 PM</TimeEntered><ArtistName>Katherine Wang</ArtistName><ArtTitle>Bluejay</ArtTitle><Dimensions>12" x 12"</Dimensions><Medium>Watercolor and ink</Medium><Price></Price><ImagePath>C:\Inetpub\vhosts\planoartassociation.org\httpdocs\App_Data\Uploaded_Image_Libraries\Eastern_Impressions\wkatherine114.gmail.com\IMG_4001.jpg</ImagePath></ImageInfo>