<ImageInfo><CustomerName>Marilee Vergati Haynes</CustomerName><CustomerPhone>214-893-8463</CustomerPhone><CustomerEmail>marilee@vergati.com</CustomerEmail><TimeEntered>9/12/2018:2:17 PM</TimeEntered><ArtistName>Marilee Vergati Haynes</ArtistName><ArtTitle>Incognito in Galapagos</ArtTitle><Dimensions>18X20</Dimensions><Medium>India Inks and acrylic inks</Medium><Price>$15-</Price><ImagePath>C:\Inetpub\vhosts\planoartassociation.org\httpdocs\App_Data\Uploaded_Image_Libraries\Global_Reflections\marilee.vergati.com\Marilee Vergati Haynes_Incognito_In_Galapagos_GlobalReflections.jpg</ImagePath></ImageInfo>